prosail/FourSAIL.py
prosail/__init__.py
prosail/light_spectra.txt
prosail/prospect5_spectra.txt
prosail/prospect_d.py
prosail/prospect_d_spectra.txt
prosail/sail_model.py
prosail/soil_reflectance.txt
prosail/spectral_library.py
prosail-2.0.5.dist-info/METADATA
prosail-2.0.5.dist-info/WHEEL
prosail-2.0.5.dist-info/top_level.txt
prosail-2.0.5.dist-info/RECORD
